assetutilities/__init__.py
assetutilities/__main__.py
assetutilities/calculation.py
assetutilities/engine.py
assetutilities/calculations/polynomial.py
assetutilities/common/ApplicationManager.py
assetutilities/common/__init__.py
assetutilities/common/data.py
assetutilities/common/data_management.py
assetutilities/common/database.py
assetutilities/common/file_edit.py
assetutilities/common/file_edit_concatenate.py
assetutilities/common/file_edit_split.py
assetutilities/common/file_management.py
assetutilities/common/pytest_utilities.py
assetutilities/common/saveData.py
assetutilities/common/set_logging.py
assetutilities/common/text_analytics.py
assetutilities/common/update_deep.py
assetutilities/common/utilities.py
assetutilities/common/visualization.py
assetutilities/common/visualization_components.py
assetutilities/common/visualizations.py
assetutilities/common/word_utilities.py
assetutilities/common/ymlInput.py
assetutilities/common/yml_utilities.py
assetutilities/common/download_data/dwnld_from_zipurl.py
assetutilities/common/reportgen/__init__.py
assetutilities/common/reportgen/decorator.py
assetutilities/common/reportgen/dom.py
assetutilities/common/reportgen/doris_writers.py
assetutilities/common/reportgen/reportgen.py
assetutilities/common/reportgen/writers.py
assetutilities/common/visualization/__init__.py
assetutilities/common/visualization/picture_manipulation.py
assetutilities/common/visualization/visualization_common.py
assetutilities/common/visualization/visualization_polar.py
assetutilities/common/visualization/visualization_templates_matplotlib.py
assetutilities/common/visualization/visualization_templates_plotly.py
assetutilities/common/visualization/visualization_xy.py
assetutilities/common/webscraping/bs4_router.py
assetutilities/common/webscraping/loopnet_scraper.py
assetutilities/common/webscraping/scrapper_bs4.py
assetutilities/common/webscraping/scrapper_scrapy.py
assetutilities/common/webscraping/web_scraping.py
assetutilities-0.0.8.dist-info/licenses/LICENSE
assetutilities-0.0.8.dist-info/METADATA
assetutilities-0.0.8.dist-info/WHEEL
assetutilities-0.0.8.dist-info/top_level.txt
assetutilities-0.0.8.dist-info/RECORD
