Metadata-Version: 2.4
Name: assetutilities
Version: 0.0.8
Summary: utilities for general use
Author-email: Vamsee Achanta <vamsee.achanta@aceengineer.com>
License: MIT
Requires-Python: >=3.8
License-File: LICENSE
Dynamic: license-file
